minimax_mcp/__init__.py
minimax_mcp/__main__.py
minimax_mcp/client.py
minimax_mcp/const.py
minimax_mcp/exceptions.py
minimax_mcp/server.py
minimax_mcp/utils.py
minimax_mcp-0.0.18.dist-info/licenses/LICENSE
minimax_mcp-0.0.18.dist-info/METADATA
minimax_mcp-0.0.18.dist-info/WHEEL
minimax_mcp-0.0.18.dist-info/entry_points.txt
minimax_mcp-0.0.18.dist-info/top_level.txt
minimax_mcp-0.0.18.dist-info/RECORD
